pyfingridapi/__init__.py
pyfingridapi/fingridapi.py
pyfingridapi-0.1.1.dist-info/METADATA
pyfingridapi-0.1.1.dist-info/WHEEL
pyfingridapi-0.1.1.dist-info/licenses/LICENSE
pyfingridapi-0.1.1.dist-info/RECORD
