Metadata-Version: 2.3
Name: pyfingridapi
Version: 0.1.1
Summary: This module is intented for easy access to fingrid API
Author-email: Aku Nivala <aku.nivala@otx.fi>
Keywords: API,Fingrid,FingridApi,FingridOpenData
Classifier: License :: OSI Approved :: MIT License
Classifier: Programming Language :: Python
Requires-Python: >=3.8
Requires-Dist: httpx<1.0.0,>=0.27.2
Requires-Dist: pydantic<3.0.0,>=2.9.2
Provides-Extra: build
Requires-Dist: twine; extra == 'build'
Provides-Extra: test
Requires-Dist: pytest; extra == 'test'
Requires-Dist: pytest-order; extra == 'test'
